better_abc/__init__.py
better_abc/better_abc.py
better_abc-0.0.3.dist-info/LICENSE
better_abc-0.0.3.dist-info/METADATA
better_abc-0.0.3.dist-info/WHEEL
better_abc-0.0.3.dist-info/top_level.txt
better_abc-0.0.3.dist-info/RECORD
